elmat/__init__.py
elmat/__main__.py
elmat/config.py
elmat/elmat_osadl.py
elmat/format.py
elmat/var/elmat.json
elmat-0.1.16.dist-info/LICENSE
elmat-0.1.16.dist-info/METADATA
elmat-0.1.16.dist-info/WHEEL
elmat-0.1.16.dist-info/entry_points.txt
elmat-0.1.16.dist-info/top_level.txt
elmat-0.1.16.dist-info/RECORD
